vnpy_xtdata/__init__.py
vnpy_xtdata/xt_datafeed.py
vnpy_xtdata/xt_datapub.py
vnpy_xtdata-2.0.0.dist-info/licenses/LICENSE
vnpy_xtdata-2.0.0.dist-info/METADATA
vnpy_xtdata-2.0.0.dist-info/WHEEL
vnpy_xtdata-2.0.0.dist-info/top_level.txt
vnpy_xtdata-2.0.0.dist-info/RECORD
