Metadata-Version: 2.4
Name: vnpy_xtdata
Version: 2.0.0
Summary: Xtquant datafeed/pub interface.
Author-email: YQ Tsui <qianyun210603@hotmail.com>
License-Expression: MIT
Keywords: quant,quantitative,investment,trading,algotrading,data
Classifier: Development Status :: 5 - Production/Stable
Classifier: Operating System :: Microsoft :: Windows
Classifier: Programming Language :: Python :: 3
Classifier: Programming Language :: Python :: 3.11
Classifier: Programming Language :: Python :: 3.12
Classifier: Programming Language :: Python :: 3.13
Classifier: Programming Language :: Python :: Implementation :: CPython
Classifier: Topic :: Office/Business :: Financial :: Investment
Classifier: Natural Language :: Chinese (Simplified)
Classifier: Typing :: Typed
Requires-Python: >=3.11
License-File: LICENSE
Requires-Dist: xtquant>=250516.1.1
Requires-Dist: filelock>=3
Requires-Dist: pandas>=2
Provides-Extra: dev
Requires-Dist: ruff; extra == "dev"
Requires-Dist: setuptools_scm>=8; extra == "dev"
Requires-Dist: setuptools>=64; extra == "dev"
Requires-Dist: wheel; extra == "dev"
Dynamic: license-file
